git_set_commit_status/__init__.py
git_set_commit_status/consts.py
git_set_commit_status/set_status.py
git_set_commit_status/utils.py
git_set_commit_status-0.1.dist-info/LICENSE
git_set_commit_status-0.1.dist-info/METADATA
git_set_commit_status-0.1.dist-info/WHEEL
git_set_commit_status-0.1.dist-info/top_level.txt
git_set_commit_status-0.1.dist-info/RECORD
